Workbook

Sheet Portada
B2: MODELO FINANCIERO – PROYECTO INMOBILIARIO
B3: Flujo de caja · Cronograma valorizado · Estado de resultados · Indicadores
B5: Proyecto: | C5: VILLA EL MILAGRO – AVN, Programa Techo Propio
B6: Empresa desarrolladora: | C6: INVERSIONES ESTRATÉGICAS INTEGRALES S.A.C.
B7: Elaborado por: | C7: Enrique Huidobro – Economista (RUC 10723712039)
B8: Fecha: | C8: 31/07/2026
B9: Moneda: | C9: Soles (S/)
B10: Destino: | C10: Sustento para carta fianza ante empresas aseguradoras
B12: CONTENIDO DEL LIBRO
B13: 1. Supuestos | C13: Parámetros editables del proyecto (celdas amarillas).
B14: 2. Cronograma_Valorizado | C14: Avance de obra y desembolsos bancarios por mes.
B15: 3. Flujo_Caja | C15: Ingresos, egresos y flujo neto mensual (24 meses).
B16: 4. Estado_Resultados | C16: P&L proyectado, utilidad y márgenes.
B17: 5. Resumen | C17: Indicadores: VAN, TIR, ROI, apalancamiento.
B19: Cómo usar: edite solo las celdas amarillas (inputs). Todo lo demás se recalcula automáticamente.

Sheet Supuestos
A1: SUPUESTOS Y PARÁMETROS DEL PROYECTO
A3: 1. DATOS GENERALES
A4: Nombre del proyecto | B4: VILLA EL MILAGRO (AVN – Techo Propio) | C4: Editable
A5: Ubicación | B5: [Distrito, Provincia] | C5: Completar
A6: Horizonte de evaluación (meses) | B6: 24
A7: Área techada vendible (m²) | B7: 3009.395
A8: N° de unidades inmobiliarias | B8: 20
A10: 2. INGRESOS Y VENTAS
A11: Precio de venta promedio por unidad (S/) | B11: 560000
A12: Ventas totales del proyecto (S/) | B12: =B8*B11
A13: Cuota inicial de clientes (%) | B13: 0.1 | C13: % que paga el cliente durante la obra
A14: Saldo financiado por crédito hipotecario (%) | B14: =1-B13
A16: 3. COSTOS DEL PROYECTO
A17: Costo del terreno (S/) | B17: 2500000
A18: Costo total de construcción (S/) | B18: 3998621.7
A19: Costo de construcción por m² (S/) | B19: =B18/B7
A20: Licencias, proyectos y estudios (% de construcción) | B20: 0.06
A21: Monto licencias/proyectos (S/) | B21: =B18*B20
A22: Gastos de comercialización (% de ventas) | B22: 0.03
A23: Monto comercialización (S/) | B23: =B12*B22
A24: Gastos administrativos / gerencia (% de ventas) | B24: 0.04
A25: Monto administrativos (S/) | B25: =B12*B24
A27: 4. FINANCIAMIENTO / GARANTÍA (CARTA FIANZA)
A28: Línea de financiamiento (% de la construcción) | B28: 0.6 | C28: Porcentaje de la obra respaldado por financiamiento / carta fianza
A29: Monto máximo de la línea (S/) | B29: =B18*B28
A30: Tasa de interés anual (TEA) | B30: 0.12
A31: Tasa de interés mensual (TEM) | B31: =(1+B30)^(1/12)-1
A33: 5. EVALUACIÓN ECONÓMICA
A34: Tasa de descuento anual (COK) | B34: 0.15
A35: Tasa de descuento mensual | B35: =(1+B34)^(1/12)-1
A36: Impuesto a la renta (%) | B36: 0.295
A39: Leyenda: Celdas amarillas = datos editables (inputs). Celdas blancas = calculadas por fórmula.

Sheet Cronograma_Valorizado
A1: CRONOGRAMA VALORIZADO DE OBRA Y CALENDARIO DE DESEMBOLSOS
A3: Concepto | B3: Total | C3: Mes 1 | D3: Mes 2 | E3: Mes 3 | F3: Mes 4 | G3: Mes 5 | H3: Mes 6 | I3: Mes 7 | J3: Mes 8 | K3: Mes 9 | L3: Mes 10 | M3: Mes 11 | N3: Mes 12 | O3: Mes 13 | P3: Mes 14 | Q3: Mes 15 | R3: Mes 16 | S3: Mes 17 | T3: Mes 18 | U3: Mes 19 | V3: Mes 20 | W3: Mes 21 | X3: Mes 22 | Y3: Mes 23 | Z3: Mes 24
A4: Perfil de avance de obra (peso S-curve) | B4: =SUM(C4:Z4) | C4: 0 | D4: 0 | E4: 0 | F4: 2 | G4: 3 | H4: 4 | I4: 5 | J4: 6 | K4: 7 | L4: 8 | M4: 8 | N4: 8 | O4: 8 | P4: 8 | Q4: 7 | R4: 7 | S4: 6 | T4: 5 | U4: 4 | V4: 3 | W4: 2 | X4: 0 | Y4: 0 | Z4: 0
A5: % de avance del mes | B5: =SUM(C5:Z5) | C5: =C4/$B$4 | D5: =D4/$B$4 | E5: =E4/$B$4 | F5: =F4/$B$4 | G5: =G4/$B$4 | H5: =H4/$B$4 | I5: =I4/$B$4 | J5: =J4/$B$4 | ... Z5: =Z4/$B$4
A6: Valorización de obra del mes (S/) | B6: =SUM(C6:Z6) | C6: =C5*Supuestos!$B$18 | D6: =D5*Supuestos!$B$18 | E6: =E5*Supuestos!$B$18 | F6: =F5*Supuestos!$B$18 | G6: =G5*Supuestos!$B$18 | H6: =H5*Supuestos!$B$18 | I6: =I5*Supuestos!$B$18 | J6: =J5*Supuestos!$B$18 | ... Z6: =Z5*Supuestos!$B$18
A7: Valorización acumulada (S/) | C7: =C6 | D7: =C7+D6 | E7: =D7+E6 | F7: =E7+F6 | G7: =F7+G6 | H7: =G7+H6 | I7: =H7+I6 | J7: =I7+J6 | K7: =J7+K6 | ... Z7: =Y7+Z6
A8: % avance acumulado | C8: =C7/Supuestos!$B$18 | D8: =D7/Supuestos!$B$18 | E8: =E7/Supuestos!$B$18 | F8: =F7/Supuestos!$B$18 | G8: =G7/Supuestos!$B$18 | H8: =H7/Supuestos!$B$18 | I8: =I7/Supuestos!$B$18 | J8: =J7/Supuestos!$B$18 | ... Z8: =Z7/Supuestos!$B$18
A10: Desembolso de financiamiento del mes (S/) | B10: =SUM(C10:Z10) | C10: =C6*Supuestos!$B$28 | D10: =D6*Supuestos!$B$28 | E10: =E6*Supuestos!$B$28 | F10: =F6*Supuestos!$B$28 | G10: =G6*Supuestos!$B$28 | H10: =H6*Supuestos!$B$28 | I10: =I6*Supuestos!$B$28 | J10: =J6*Supuestos!$B$28 | ... Z10: =Z6*Supuestos!$B$28
A11: Desembolso de financiamiento acumulado (S/) | C11: =C10 | D11: =C11+D10 | E11: =D11+E10 | F11: =E11+F10 | G11: =F11+G10 | H11: =G11+H10 | I11: =H11+I10 | J11: =I11+J10 | K11: =J11+K10 | ... Z11: =Y11+Z10
A13: Nota: el desembolso bancario se ata a la valorización mensual de obra (avance físico real). Ajuste el perfil S-curve (fila azul) según el cronograma de ejecución del proyecto.

Sheet Flujo_Caja
A1: FLUJO DE CAJA DEL PROYECTO (mensual, en Soles)
A3: Concepto | B3: Total | C3: Mes 1 | D3: Mes 2 | E3: Mes 3 | F3: Mes 4 | G3: Mes 5 | H3: Mes 6 | I3: Mes 7 | J3: Mes 8 | K3: Mes 9 | L3: Mes 10 | M3: Mes 11 | N3: Mes 12 | O3: Mes 13 | P3: Mes 14 | Q3: Mes 15 | R3: Mes 16 | S3: Mes 17 | T3: Mes 18 | U3: Mes 19 | V3: Mes 20 | W3: Mes 21 | X3: Mes 22 | Y3: Mes 23 | Z3: Mes 24
A4: DISTRIBUCIÓN TEMPORAL (perfiles editables)
A5: Perfil de recaudo de cuota inicial (peso) | B5: =SUM(C5:Z5) | C5: 0 | D5: 1 | E5: 1 | F5: 1 | G5: 1 | H5: 1 | I5: 1 | J5: 1 | K5: 1 | L5: 1 | M5: 1 | N5: 1 | O5: 1 | P5: 1 | Q5: 1 | R5: 1 | S5: 1 | T5: 1 | U5: 1 | V5: 1 | W5: 0 | X5: 0 | Y5: 0 | Z5: 0
A6: Perfil de entrega / cobro de saldo (peso) | B6: =SUM(C6:Z6) | C6: 0 | D6: 0 | E6: 0 | F6: 0 | G6: 0 | H6: 0 | I6: 0 | J6: 0 | K6: 0 | L6: 0 | M6: 0 | N6: 0 | O6: 0 | P6: 0 | Q6: 0 | R6: 0 | S6: 0 | T6: 0 | U6: 0 | V6: 0 | W6: 0 | X6: 1 | Y6: 2 | Z6: 2
A8: A. INGRESOS
A9: Cuota inicial de clientes | B9: =SUM(C9:Z9) | C9: =(C$5/$B$5)*Supuestos!$B$12*Supuestos!$B$13 | D9: =(D$5/$B$5)*Supuestos!$B$12*Supuestos!$B$13 | E9: =(E$5/$B$5)*Supuestos!$B$12*Supuestos!$B$13 | F9: =(F$5/$B$5)*Supuestos!$B$12*Supuestos!$B$13 | G9: =(G$5/$B$5)*Supuestos!$B$12*Supuestos!$B$13 | H9: =(H$5/$B$5)*Supuestos!$B$12*Supuestos!$B$13 | I9: =(I$5/$B$5)*Supuestos!$B$12*Supuestos!$B$13 | J9: =(J$5/$B$5)*Supuestos!$B$12*Supuestos!$B$13 | ... Z9: =(Z$5/$B$5)*Supuestos!$B$12*Supuestos!$B$13
A10: Cobro de saldo (créditos hipotecarios) | B10: =SUM(C10:Z10) | C10: =(C$6/$B$6)*Supuestos!$B$12*Supuestos!$B$14 | D10: =(D$6/$B$6)*Supuestos!$B$12*Supuestos!$B$14 | E10: =(E$6/$B$6)*Supuestos!$B$12*Supuestos!$B$14 | F10: =(F$6/$B$6)*Supuestos!$B$12*Supuestos!$B$14 | G10: =(G$6/$B$6)*Supuestos!$B$12*Supuestos!$B$14 | H10: =(H$6/$B$6)*Supuestos!$B$12*Supuestos!$B$14 | I10: =(I$6/$B$6)*Supuestos!$B$12*Supuestos!$B$14 | J10: =(J$6/$B$6)*Supuestos!$B$12*Supuestos!$B$14 | ... Z10: =(Z$6/$B$6)*Supuestos!$B$12*Supuestos!$B$14
A11: Desembolsos de financiamiento | B11: =SUM(C11:Z11) | C11: =Cronograma_Valorizado!C$10 | D11: =Cronograma_Valorizado!D$10 | E11: =Cronograma_Valorizado!E$10 | F11: =Cronograma_Valorizado!F$10 | G11: =Cronograma_Valorizado!G$10 | H11: =Cronograma_Valorizado!H$10 | I11: =Cronograma_Valorizado!I$10 | J11: =Cronograma_Valorizado!J$10 | ... Z11: =Cronograma_Valorizado!Z$10
A12: Total ingresos | B12: =SUM(C12:Z12) | C12: =SUM(C9:C11) | D12: =SUM(D9:D11) | E12: =SUM(E9:E11) | F12: =SUM(F9:F11) | G12: =SUM(G9:G11) | H12: =SUM(H9:H11) | I12: =SUM(I9:I11) | J12: =SUM(J9:J11) | ... Z12: =SUM(Z9:Z11)
A14: B. EGRESOS OPERATIVOS
A15: Compra de terreno | B15: =SUM(C15:Z15) | C15: =-Supuestos!$B$17 | D15: 0 | E15: 0 | F15: 0 | G15: 0 | H15: 0 | I15: 0 | J15: 0 | K15: 0 | L15: 0 | M15: 0 | N15: 0 | O15: 0 | P15: 0 | Q15: 0 | R15: 0 | S15: 0 | T15: 0 | U15: 0 | V15: 0 | W15: 0 | X15: 0 | Y15: 0 | Z15: 0
A16: Costo de construcción (valorización de obra) | B16: =SUM(C16:Z16) | C16: =-Cronograma_Valorizado!C$6 | D16: =-Cronograma_Valorizado!D$6 | E16: =-Cronograma_Valorizado!E$6 | F16: =-Cronograma_Valorizado!F$6 | G16: =-Cronograma_Valorizado!G$6 | H16: =-Cronograma_Valorizado!H$6 | I16: =-Cronograma_Valorizado!I$6 | J16: =-Cronograma_Valorizado!J$6 | ... Z16: =-Cronograma_Valorizado!Z$6
A17: Licencias, proyectos y estudios | B17: =SUM(C17:Z17) | C17: =-Supuestos!$B$21/3 | D17: =-Supuestos!$B$21/3 | E17: =-Supuestos!$B$21/3 | F17: 0 | G17: 0 | H17: 0 | I17: 0 | J17: 0 | K17: 0 | L17: 0 | M17: 0 | N17: 0 | O17: 0 | P17: 0 | Q17: 0 | R17: 0 | S17: 0 | T17: 0 | U17: 0 | V17: 0 | W17: 0 | X17: 0 | Y17: 0 | Z17: 0
A18: Gastos de comercialización | B18: =SUM(C18:Z18) | C18: 0 | D18: 0 | E18: =-Supuestos!$B$23/20 | F18: =-Supuestos!$B$23/20 | G18: =-Supuestos!$B$23/20 | H18: =-Supuestos!$B$23/20 | I18: =-Supuestos!$B$23/20 | J18: =-Supuestos!$B$23/20 | K18: =-Supuestos!$B$23/20 | L18: =-Supuestos!$B$23/20 | ... X18: =-Supuestos!$B$23/20 | Y18: 0 | Z18: 0
A19: Gastos administrativos / gerencia | B19: =SUM(C19:Z19) | C19: =-Supuestos!$B$25/24 | D19: =-Supuestos!$B$25/24 | E19: =-Supuestos!$B$25/24 | F19: =-Supuestos!$B$25/24 | G19: =-Supuestos!$B$25/24 | H19: =-Supuestos!$B$25/24 | I19: =-Supuestos!$B$25/24 | J19: =-Supuestos!$B$25/24 | ... Z19: =-Supuestos!$B$25/24
A20: Total egresos operativos | B20: =SUM(C20:Z20) | C20: =SUM(C15:C19) | D20: =SUM(D15:D19) | E20: =SUM(E15:E19) | F20: =SUM(F15:F19) | G20: =SUM(G15:G19) | H20: =SUM(H15:H19) | I20: =SUM(I15:I19) | J20: =SUM(J15:J19) | ... Z20: =SUM(Z15:Z19)
A22: C. SERVICIO DE LA DEUDA / FINANCIAMIENTO
A23: Saldo inicial de la línea | C23: 0 | D23: =C27 | E23: =D27 | F23: =E27 | G23: =F27 | H23: =G27 | I23: =H27 | J23: =I27 | K23: =J27 | ... Z23: =Y27
A24: (+) Desembolso del mes | B24: =SUM(C24:Z24) | C24: =Cronograma_Valorizado!C$10 | D24: =Cronograma_Valorizado!D$10 | E24: =Cronograma_Valorizado!E$10 | F24: =Cronograma_Valorizado!F$10 | G24: =Cronograma_Valorizado!G$10 | H24: =Cronograma_Valorizado!H$10 | I24: =Cronograma_Valorizado!I$10 | J24: =Cronograma_Valorizado!J$10 | ... Z24: =Cronograma_Valorizado!Z$10
A25: (-) Amortización del mes | B25: =SUM(C25:Z25) | C25: =-(C$6/$B$6)*Cronograma_Valorizado!$B$10 | D25: =-(D$6/$B$6)*Cronograma_Valorizado!$B$10 | E25: =-(E$6/$B$6)*Cronograma_Valorizado!$B$10 | F25: =-(F$6/$B$6)*Cronograma_Valorizado!$B$10 | G25: =-(G$6/$B$6)*Cronograma_Valorizado!$B$10 | H25: =-(H$6/$B$6)*Cronograma_Valorizado!$B$10 | I25: =-(I$6/$B$6)*Cronograma_Valorizado!$B$10 | J25: =-(J$6/$B$6)*Cronograma_Valorizado!$B$10 | ... Z25: =-(Z$6/$B$6)*Cronograma_Valorizado!$B$10
A26: (-) Intereses del mes (gasto financiero) | B26: =SUM(C26:Z26) | C26: =-C23*Supuestos!$B$31 | D26: =-D23*Supuestos!$B$31 | E26: =-E23*Supuestos!$B$31 | F26: =-F23*Supuestos!$B$31 | G26: =-G23*Supuestos!$B$31 | H26: =-H23*Supuestos!$B$31 | I26: =-I23*Supuestos!$B$31 | J26: =-J23*Supuestos!$B$31 | ... Z26: =-Z23*Supuestos!$B$31
A27: Saldo final de la línea | C27: =C23+C24+C25 | D27: =D23+D24+D25 | E27: =E23+E24+E25 | F27: =F23+F24+F25 | G27: =G23+G24+G25 | H27: =H23+H24+H25 | I27: =I23+I24+I25 | J27: =J23+J24+J25 | ... Z27: =Z23+Z24+Z25
A29: D. FLUJOS DE CAJA
A30: Flujo económico del mes (sin financiamiento) | B30: =SUM(C30:Z30) | C30: =C9+C10+C20 | D30: =D9+D10+D20 | E30: =E9+E10+E20 | F30: =F9+F10+F20 | G30: =G9+G10+G20 | H30: =H9+H10+H20 | I30: =I9+I10+I20 | J30: =J9+J10+J20 | ... Z30: =Z9+Z10+Z20
A31: Flujo económico acumulado | C31: =C30 | D31: =C31+D30 | E31: =D31+E30 | F31: =E31+F30 | G31: =F31+G30 | H31: =G31+H30 | I31: =H31+I30 | J31: =I31+J30 | K31: =J31+K30 | ... Z31: =Y31+Z30
A32: Flujo financiero del mes (con financiamiento) | B32: =SUM(C32:Z32) | C32: =C30+C24+C25+C26 | D32: =D30+D24+D25+D26 | E32: =E30+E24+E25+E26 | F32: =F30+F24+F25+F26 | G32: =G30+G24+G25+G26 | H32: =H30+H24+H25+H26 | I32: =I30+I24+I25+I26 | J32: =J30+J24+J25+J26 | ... Z32: =Z30+Z24+Z25+Z26
A33: Flujo financiero acumulado (caja del proyecto) | C33: =C32 | D33: =C33+D32 | E33: =D33+E32 | F33: =E33+F32 | G33: =F33+G32 | H33: =G33+H32 | I33: =H33+I32 | J33: =I33+J32 | K33: =J33+K32 | ... Z33: =Y33+Z32

Sheet Estado_Resultados
A1: ESTADO DE RESULTADOS PROYECTADO DEL PROYECTO
A3: INGRESOS
A4: Ventas totales del proyecto | B4: =Supuestos!$B$12
A6: COSTO DE VENTAS
A7: (-) Costo del terreno | B7: =-Supuestos!$B$17
A8: (-) Costo de construcción | B8: =-Supuestos!$B$18
A9: (-) Licencias, proyectos y estudios | B9: =-Supuestos!$B$21
A10: UTILIDAD BRUTA | B10: =B4+B7+B8+B9
A11: Margen bruto | B11: =B10/B4
A13: GASTOS OPERATIVOS
A14: (-) Gastos de comercialización | B14: =-Supuestos!$B$23
A15: (-) Gastos administrativos / gerencia | B15: =-Supuestos!$B$25
A16: UTILIDAD OPERATIVA | B16: =B10+B14+B15
A18: RESULTADO FINANCIERO E IMPUESTOS
A19: (-) Gastos financieros (intereses de la línea) | B19: =Flujo_Caja!$B$26
A20: UTILIDAD ANTES DE IMPUESTOS | B20: =B16+B19
A21: (-) Impuesto a la renta | B21: =-MAX(B20,0)*Supuestos!$B$36
A22: UTILIDAD NETA | B22: =B20+B21
A23: Margen neto | B23: =B22/B4
A26: Nota: cifras en valores netos (sin IGV). El intereses proviene del flujo de caja financiero.

Sheet Resumen
A1: RESUMEN EJECUTIVO E INDICADORES
A3: INVERSIÓN Y ESTRUCTURA
A4: Ventas totales (S/) | B4: =Supuestos!$B$12
A5: Inversión total del proyecto (S/) | B5: =Supuestos!$B$17+Supuestos!$B$18+Supuestos!$B$21+Supuestos!$B$23+Supuestos!$B$25
A6: Monto máximo de financiamiento / carta fianza (S/) | B6: =Supuestos!$B$29
A7: Apalancamiento (financiamiento / inversión) | B7: =Supuestos!$B$29/B5
A8: Aporte propio del desarrollador (S/) | B8: =B5-Supuestos!$B$29
A10: RENTABILIDAD
A11: Utilidad neta (S/) | B11: =Estado_Resultados!B22
A12: Margen neto | B12: =Estado_Resultados!B23
A13: ROI sobre inversión total | B13: =Estado_Resultados!B22/B5
A15: EVALUACIÓN ECONÓMICA (sin financiamiento)
A16: VAN económico (S/) | B16: =NPV(Supuestos!$B$35,Flujo_Caja!C30:Z30)
A17: TIR económica mensual | B17: =IRR(Flujo_Caja!C30:Z30)
A18: TIR económica anual | B18: =(1+B17)^12-1
A20: EVALUACIÓN FINANCIERA (con financiamiento)
A21: VAN financiero (S/) | B21: =NPV(Supuestos!$B$35,Flujo_Caja!C32:Z32)
A22: TIR financiera mensual | B22: =IRR(Flujo_Caja!C32:Z32)
A23: TIR financiera anual | B23: =(1+B22)^12-1
A26: El VAN se calcula con la tasa de descuento mensual (COK) de la hoja Supuestos. La TIR se anualiza como (1+TIR mensual)^12-1.
